pixcompress/__init__.py
pixcompress/cli.py
pixcompress/core.py
pixcompress_ruskaruma-0.1.0.dist-info/licenses/LICENSE
pixcompress_ruskaruma-0.1.0.dist-info/METADATA
pixcompress_ruskaruma-0.1.0.dist-info/WHEEL
pixcompress_ruskaruma-0.1.0.dist-info/entry_points.txt
pixcompress_ruskaruma-0.1.0.dist-info/top_level.txt
pixcompress_ruskaruma-0.1.0.dist-info/RECORD
