Metadata-Version: 2.4
Name: pixcompress-ruskaruma
Version: 0.1.0
Summary: Simple image compression tool
Author-email: Ruskaruma <ruskaruma.gg@gmail.com>
License-Expression: MIT
Requires-Python: >=3.9
License-File: LICENSE
Requires-Dist: Pillow>=9.0
Requires-Dist: click>=8.0
Dynamic: license-file
